README.rst
setup.py
Kulka.egg-info/PKG-INFO
Kulka.egg-info/SOURCES.txt
Kulka.egg-info/dependency_links.txt
Kulka.egg-info/top_level.txt
kulka/__init__.py
kulka/connection/__init__.py
kulka/connection/baseconnection.py
kulka/connection/bluezconnection.py
kulka/connection/socketconnection.py
kulka/connection/exceptions/__init__.py
kulka/connection/exceptions/connectionfailed.py
kulka/connection/exceptions/connectionlost.py
kulka/core/__init__.py
kulka/core/core.py
kulka/core/logger.py
kulka/request/__init__.py
kulka/request/corerequest.py
kulka/request/kulkarequest.py
kulka/request/request.py
kulka/request/roll.py
kulka/request/setbackled.py
kulka/request/setinactivitytimeout.py
kulka/request/setrgb.py
kulka/request/sleep.py
kulka/response/__init__.py
kulka/response/asyncpacket.py
kulka/response/parser.py
kulka/response/responsepacket.py