Metadata-Version: 1.1
Name: Kulka
Version: 0.3.0
Summary: Sphero client
Home-page: https://github.com/karulis/pybluez
Author: Karol Szuster
Author-email: szuster.karol@gmail.com
License: GPL
Download-URL: https://github.com/karulis/pybluez
Platform: UNKNOWN
Classifier: Development Status :: 4 - Beta
Classifier: License :: OSI Approved :: GNU General Public License (GPL)
Classifier: Programming Language :: Python
Classifier: Programming Language :: Python :: 2
Classifier: Programming Language :: Python :: 3
Classifier: Topic :: Communications
